MapMet/__init__.py
MapMet/segmentation.py
MapMet/utils.py
MapMet-0.0.12.dist-info/METADATA
MapMet-0.0.12.dist-info/WHEEL
MapMet-0.0.12.dist-info/top_level.txt
MapMet-0.0.12.dist-info/RECORD
