Metadata-Version: 2.1
Name: MapMet
Version: 0.0.12
Summary: MapMet Package
Author: Taschner-Mandl Group
License: UNKNOWN
Keywords: python
Platform: UNKNOWN
Classifier: Programming Language :: Python :: 3
Classifier: Operating System :: Unix
Requires-Dist: certifi (==2022.5.18.1)
Requires-Dist: ExifRead (==3.0.0)
Requires-Dist: imageio (==2.19.2)
Requires-Dist: line-profiler (==3.5.1)
Requires-Dist: mpmath (==1.2.1)
Requires-Dist: networkx (==2.8.2)
Requires-Dist: nose (==1.3.7)
Requires-Dist: numpy (==1.22.4)
Requires-Dist: opencv-python (==4.5.5.64)
Requires-Dist: pandas (==1.4.2)
Requires-Dist: Pillow (==9.1.1)
Requires-Dist: pytz (==2022.1)
Requires-Dist: PyWavelets (==1.3.0)
Requires-Dist: pyzmq (==19.0.2)
Requires-Dist: readimc (==0.6.1)
Requires-Dist: scikit-image (==0.19.2)
Requires-Dist: scipy (==1.8.1)
Requires-Dist: tifffile (==2022.5.4)
